{"آپارتمان-مسکونی-تا40متر":[{"contact":"تمام نقاط 22894611","ad_text":"اطلاعات املاک بزرگ تهران , « بی و ا سطه » , کجا به دنبال ملک می گردید تمام نقاط 22894611"},{"contact":"09124100954","ad_text":"سبلان شمالی , 35متر1خ طبقه4 تکواحدی , 3ساله باپارکینگ وانباری( بیواسطه ) 09124100954"},{"contact":"09124254840","ad_text":"مرتضوی، 40متر، ط3،خوش , نقشه،پارکینگ،انباری،MDF،کف , لمینت،2ساله،27رهن،قیمت125م 09124254840"},{"contact":"2 - 65578901","ad_text":"اندیشه فازیک , با 13م نقد صاحب آپارتمان , سند دارشوید 2 - 65578901"},{"contact":"09125003048 - 44736082","ad_text":"منطقه22 - بهترین خریدارو , فروشنده یاس2 , « پروژه بی نظیرشهیدخرازی » 09125003048 - 44736082"},{"contact":"09120570346 - 09120570349","ad_text":"اندیشه , آپارتمان از40الی120متر , با50م وام مسکن 09120570346 - 09120570349"},{"contact":"09125459005","ad_text":"*مشاورین‎املاک‏علی‎تهرانپارس* , 40متر نزدیک‎مترو10متربالکن , 1خوابه روبه‎آفتاب کم‎واحد 09125459005"},{"contact":"09127966870 ـ 77585797","ad_text":"خ دماوند خ فتحنایی , 40متر باپارکینگ فول امکانات , مقطوع 125 م 09127966870 ـ 77585797"},{"contact":"09194023117و 44458211","ad_text":"فردوس شرق - گلستان , 40متربابهترین دسترسی فول , درمجموعه فوق العاده شیک(عیوضی) 09194023117و 44458211"},{"contact":"5 - 65502811","ad_text":"اندیشه 10م به بالا1و2خوابه , 40تا120متر-آماده محضر , باوام و رهن یا معاوضه باخودرو 5 - 65502811"},{"contact":"09120570348 09120570347","ad_text":"اندیشه آپارتمانهای1و2خوابه , سنددار - آماده محضر 09120570348 09120570347"},{"contact":"65516583 - 65516604","ad_text":"اندیشه 13م نقد به بالا , 40و43و55و72مترسنددار , وام بانکی،رهن یامعاوضه با خودرو 65516583 - 65516604"},{"contact":"قرباني 09125949239","ad_text":"کهریزک،جنب مترو،شهرآفتاب , آپارتمان نوساز 40 و 60 و 75 , متری 1 الی 5 / 1 باوام بانکی قرباني 09125949239"},{"contact":"68الي 65368966","ad_text":"اندیشه با12م نقدبه بالا , 1و 2خوابه از40الی100مترباوام , رهن،سنددار،معاوضه باخودرو 68الي 65368966"},{"contact":"09121613529 - 09127653978","ad_text":"اندیشه , با 10م صاحب آپارتمان , سنددار شوید 09121613529 - 09127653978"},{"contact":"09122158179 44713434","ad_text":"منطقه22- املاک آینده , یاس 2 ، شهرک امام رضا , خرازی ، آسمان ، آرتمیس , صیاد فاز2 و... 09122158179 44713434"},{"contact":"09339690897","ad_text":"سهروردی - ملک , آپارتمان 40متر + 26متر سالن , در یک سند فقط 330 م 09339690897"},{"contact":"44766020 - 44706020","ad_text":"منطقه22 (املاک‎ایران‎زمین) , خرازی ، یاس2 ، آسمان , « بهترین خریدار وفروشنده » 44766020 - 44706020"},{"contact":"ندائي نسب 09125156256","ad_text":"منطقه 22 - خرید فروش , آرتمیس آرتمیس ندائي نسب 09125156256"},{"contact":"09124704463","ad_text":"انتهای نبرد-میدان تفحص , 37 متر با پارکینگ ط 3 , تک واحدی متری 600 / 2 م 09124704463"},{"contact":"8 - 65502816","ad_text":"اندیشه چرارهن ؟؟؟ , با28م نقدبخریدوساکن شوید , 1و2خوابه سنددارمعاوضه باخودرو 8 - 65502816"}],"آپارتمان-مسکونی-41-تا-45-متر":[{"contact":"تمام نقاط 22894611","ad_text":"اطلاعات املاک بزرگ تهران , « بی و ا سطه » , کجا به دنبال ملک می گردید تمام نقاط 22894611"},{"contact":"09359881480","ad_text":"سوم نیروهوایی 43مترتکواحد , بی پارکینگ وانباری طبقه3باآسانسور , پول لازم زیرقیمت فوری 170م 09359881480"},{"contact":"09127346248","ad_text":"مسعودیه , 42متر با پارکینگ طبقه2 , آسانسور 105م 09127346248"},{"contact":"77624142","ad_text":"خواجه نظام تیموری , 2 / 44 متر 1خوابه تکواحدی , متری400 / 3 با 15م پارکینگ 77624142"},{"contact":"اسدي 09193262860","ad_text":"خیابان ابوذر - میدان گلچین , 41متر3ساله با پارکینگ انباری , فول امکانات - طبقه اول اسدي 09193262860"},{"contact":"09191000621ـ44014952","ad_text":"شهران جنوبی 44متر 1خ , ط دوم با پارکینگ وانباری , بسیارخوش نقشه ( عابدینی) 09191000621ـ44014952"},{"contact":"09121312628","ad_text":"کمیل - پوراسلامی , 41 متر ط 2 - بازسازی , 38 م وام 22 دررهن قیمت110 م 09121312628"}],"آپارتمان-مسکونی-46-تا-50-متر":[{"contact":"09124142320","ad_text":"میدان رازی - کارگر جنوبی , 48مترتکواحدی ط4 با آسانسور , نورگیر عالی خوش نقشه - باوام 09124142320"},{"contact":"09123377012و44454171","ad_text":"فردوس غرب , 50متر 1خوابه نوساز فول , سوپرلوکس آفتابگیر دیدپارک،افشین 09123377012و44454171"},{"contact":"09104499910ـ44000670","ad_text":"فردوس غرب بهارجنوبی , 48متر یکخوابه 9ساله فول , امکانات بازسازی ( داخلی910) 09104499910ـ44000670"},{"contact":"09122462295","ad_text":"تهران نو ، 48متر ، بازسازی , ط4 بی‎آسانسور و پارکینگ ، نور و , نقشه‎ موقعیت‎عالی ، 35رهن 10وام 09122462295"},{"contact":"33789830","ad_text":"پیروزی - محصل , 48 متر 1خوابه تکواحدی 33789830"},{"contact":"بابايي 8903 - 09122186850","ad_text":"قیطریه - بر اندرزگو , 50متر-تک خواب-330میلیون , موقعیت اداری و مسکونی بابايي 8903 - 09122186850"},{"contact":"09198884749 و 33067346","ad_text":"پیروزی ، نبردشمالی(املاک) , 47 مترتکواحدط 1 انباری آسانسور , 47 رهن 70 م+ 36 م وام ونقدشما 09198884749 و 33067346"},{"contact":"09362205441","ad_text":"شهرک ولیعصر - 5 / 46متر , شیک وخوش نقشه MDF طبقه3 , 14وام + 25رهن + 58م نقد 09362205441"},{"contact":"09398610909","ad_text":"خوش نقشه ترین درجیحون , 49متر/طبقه دوم , شمالی با انباری 09398610909"},{"contact":"09338607604","ad_text":"انتهای جیحون - بر 10متری , 50مترط2باپارکینگ،انباری2کله , شیک70وام دارد40رهن20 نقد 09338607604"},{"contact":"09126599174","ad_text":"آزادگان - شهرک مرتضی گرد , 6واحد 50 متری آپارتمان , نوساز - یکجا 220 میلیون 09126599174"},{"contact":"09104977710ـ44969400","ad_text":"شهران , 47متر = 200میلیون , تماس بگیرید (ملکی) 09104977710ـ44969400"},{"contact":"09120275644","ad_text":"شریعتی - ملک , 50متر زیرهمکف نورگیر عالی , شوفاژ ، اسپیلت ( 140 م ) 09120275644"},{"contact":"پارسيان 09360703826 خط ويژه 75395","ad_text":"سعادت آباد , 50 متر تکخواب , بسیار خوش نقشه , فقط 430 م پارسيان 09360703826 خط ويژه 75395"},{"contact":"نوري 09121456672","ad_text":"پونک - کمالی , 49 متر - بدون پارکینگ , 310 م مقطوع نوري 09121456672"},{"contact":"09124401310","ad_text":"طالقانی - بهار , 47متر آپارتمان نوساز , طبقه 4 با آسانسور 09124401310"},{"contact":"09212382930ـ44818182","ad_text":"فقط مشکل پسندان تماس بگیرند , واحدهای نقلی رویایی سوپرلوکس , (نوساز)با60م وام از42تا68 , در متراژهای مختلف(شیردلان) , فردوس شرق بهترین فرعی 09212382930ـ44818182"},{"contact":"مسکن باغ صبا 88441300","ad_text":"شریعتی - روبروی ملک , 48متر1خ تکواحدی طبقه4 , باانباری 135م مسکن باغ صبا 88441300"},{"contact":"09121245440","ad_text":"دامپزشکی بعد از جیحون , 50 متر نوساز 4طبقه تکواحدی , بصورت یکجا یا تکی 09121245440"},{"contact":"09104499913ـ44000670","ad_text":"فردوس غرب , 50متر فول امکانات , نورونقشه عالی(داخلی913) 09104499913ـ44000670"},{"contact":"09123113125 پور جمشيد 44809533","ad_text":"پونک - همیلا , سازه ای رویایی و کلاسیک , 44و46مترنوساز VIP , لابی + سالن اجتماعات و ... 09123113125 پور جمشيد 44809533"},{"contact":"09370580020","ad_text":"تهرانسر , 50متر , 67نقد +33رهن +30 وام شما 09370580020"},{"contact":"09124847205","ad_text":"پونک - سیمون بولیوار , 50متر با آسانسور , طبقه2 از 3طبقه تکواحدی , پکیج و شوفاژ , خوش نقشه , 09124847205"},{"contact":"09032956606ـ44244686","ad_text":"50 متر خوش نقشه فول امکانات , * غرق نور * , نقشه مشابه 60 متری , قیمت فقط 230م (فکوری) , * فردوس شرق * 09032956606ـ44244686"}],"آپارتمان-مسکونی-51تا-55-متر":[{"contact":"33259916 و 09125337860","ad_text":"17شهریور - جهانپناه , 52متر،طبقه دوم،اپن،MDF , با انباری ، قیمت 110 میلیون 33259916 و 09125337860"},{"contact":"زماني 09196323347","ad_text":"تهرانپارس- مسکن یاسین , محدوده استخر 232 , 51مترفول امکانات،روبه آفتاب , بانقشه بی نظیر(50م رهن , دارای70م وام 65م نقدازشما) , فروش یا معاوضه (فوری) زماني 09196323347"},{"contact":"44066938 - 09300839008","ad_text":"( فرصت را از دست ندهید ) , زوج های جوان بشتابید !! , 55متر / full امکانات , متری 800 / 4 = 264م (فرهاد , * مرزداران * 44066938 - 09300839008"},{"contact":"صادقي 09194090290","ad_text":"پیامبرغربی - جهاداکبر , 53 متر ط سوم 4طبقه 18ساله , 16 واحدی با پارکینگ 215 م صادقي 09194090290"},{"contact":"09120378057ـ44892965","ad_text":"جنت آباد چهارباغ شرقی , 52متر1خ روبه آفتاب فول , بازسازی ط سوم180م (مصدق) 09120378057ـ44892965"},{"contact":"09121062367","ad_text":"« نامجو » , 53متر نوساز کلیدنخورده , فول امکانات 09121062367"},{"contact":"09121139477","ad_text":"* اتوبان رسالت * , تهرانپارس - 54متری , نوساز - با کلیه امکانات 09121139477"},{"contact":"09378081488ـ44014952","ad_text":"کاشانی شاهین جنوبی , 55متر یکخوابه = 200م , تماس بگیرید (قاسمی) 09378081488ـ44014952"},{"contact":"09124034063","ad_text":"گلبرگ-مدنی شمالی-کوچه رضایی , 54متر 2خواب ط3 باانباری , وپارکینگ بدون آسانسور 09124034063"},{"contact":"09125650085و44610163","ad_text":"54متر 1خ نوساز , تکواحدی فاقد پارکینگ , 150نقد + 55رهن از ما , 70م وام از شما(فرمانی) , شاهین شمالی 09125650085و44610163"},{"contact":"22680005 - 09128983083","ad_text":"دارآباد , 55 و 80متری , متری500 / 5م‏امکانات‏کامل/عباسی 22680005 - 09128983083"},{"contact":"پرهام 09382340824","ad_text":"سی متری جی-16متری امیری , 55متر 1خوابه باانباری , شیک وخوش نقشه آفتابگیر پرهام 09382340824"},{"contact":"09125000611","ad_text":"ولیعصر - امیریه , 52 متر 2خواب کم واحد فول , خوش نقشه، بی واسطه فوری 160م 09125000611"},{"contact":"09121719565 ـ 66751093","ad_text":"کالج - ابیورد , 52 متر - پارکینگ و انباری , حیاط خلوت ( شمس ) 09121719565 ـ 66751093"},{"contact":"09197544215","ad_text":"« صادقیه - گلاب » , 55متر تکواحدی طبقه چهارم , با کلیه امکانات 09197544215"},{"contact":"09104499943ـ44000670","ad_text":"کاشانی سازمان شمالی , 55متر فول امکانات آفتابگیر , کم واحدتخلیه265م(داخلی943) 09104499943ـ44000670"},{"contact":"09372113098 44046713","ad_text":"کاشانی،مهران،فهیمی , نسل جدیدخانه های ضدزلزله , روف گاردن،آشپزخانه مبله , نماانگلیسی 5سال ضمانت و... , 55 و 105متری تعدادی محدود 09372113098 44046713"},{"contact":"09216326032 (کارن) 44818182","ad_text":"بلوار فردوس (بهارجنوبی) , 54 متر 2خوابه طبقه چهارم , خوش نقشه با پارکینگ و انباری , فوری فروشی 207م 09216326032 (کارن) 44818182"},{"contact":"09123358715","ad_text":"جمالزاده - خیابان کلهر , 55مترفول بازسازی کامل , نور عالی،طبقه اول ، بیواسطه‏،فوری 09123358715"},{"contact":"09358135627ـ44090404","ad_text":"املاک 133 , شهران , 55متر لوکس FULL , بی نقص سالن پرده خور , 205میلیون + 50م وام , این بار عجله کنید (خرسند) 09358135627ـ44090404"},{"contact":"09124544980","ad_text":"یادگار-بین هاشمی‎ودستغیب , 52متر،پارکینگ‎،انباری ،آسانسور , 2ساله ، مناسب سرمایه‎گذاری 09124544980"},{"contact":"فلاح 09123080213 44136010","ad_text":"فردوس،سازه ای بی همتا , نمونه کارسازنده منطقه1 , مناسب زوجین جوانVIP , 45 تا 60متر / 1خ / فول , نوساز،نقشه‎واقعادیدنی , دیزاین‎شده کابینت‎های گلاس , ( 200متر لابی مجلل مبله ) , آلاچیق،آبنما،حیاط سازی , بازدید= 100%قرارداد , به همراه وام بانکی فلاح 09123080213 44136010"},{"contact":"09128145680","ad_text":"نبرد شمالی - 52متر 1خ , 14ساله ط4سندی باانباری و , آسانسور- با 15وام متری100 / 3 09128145680"},{"contact":"09123005763 ـ 77800024","ad_text":"نارمک گلبرگ شرقی , 53متر یکخوابه , فول امکانات 09123005763 ـ 77800024"},{"contact":"09195094179ـ44235071","ad_text":"55 متر نورونقشه عالی , طبقه 2 آسانسور , بازدید = خرید , فوری 210م (نیکومنش) , آیت ا... کاشانی بلوارتعاون 09195094179ـ44235071"},{"contact":"09308813397 سعيدي 23547","ad_text":"جردن - ولیعصر , فروشنده واقعی , 53متر 1خوابه , فقط 610 میلیون 09308813397 سعيدي 23547"},{"contact":"09121856403","ad_text":"فرمانیه , 2واحد 52متری نوساز تکواحدی , فول امکانات - فوری فروشی 09121856403"},{"contact":"09335860106و44285185","ad_text":"پونک-اشرفی55متر نوساز , نقشه‏ونورفوق‏العاده-فول , متری 500هزارزیرقیمت(مسکن) 09335860106و44285185"},{"contact":"22832693","ad_text":"* نیاوران * , 51 متر 2بر اتاق مستر طبقه1 , 14ساله بازسازی350نقد + 80رهن 22832693"},{"contact":"پاشازاده 09306900129","ad_text":"قائم پونک - شاهین شمالی , 53متر طبقه اول با پارکینگ , 8واحدی پاشازاده 09306900129"},{"contact":"09120784269ـ44244686","ad_text":"55متر خوش نقشه سالن پرده خور , * فول امکانات * , نقشه مشابه 65متری , قیمت فقط 220م (دایان) , * ستاری پیامبر * 09120784269ـ44244686"}],"آپارتمان-مسکونی-56-تا-60-متر":[{"contact":"( مجيدي ) 09190321154","ad_text":"ستارخان ( گلاب ) , 60 متر 1 خ نوساز تکواحدی , شدیدا\" زیرقیمت فوری 279 م ( مجيدي ) 09190321154"},{"contact":"09125162902","ad_text":"نارمک - میدان 7 , 60مترباپارکینگ وانباری،طبقه3 , آفتابگیر،تکواحد،فقط250م 09125162902"},{"contact":"09357057538ـ44014952","ad_text":"ستاری پیامبر مرکزی , 58متر یکخوابه = 220م , فول امکانات (صادقیان) 09357057538ـ44014952"},{"contact":"09128351083و22784830","ad_text":"پاسداران - هروی , 58مترکلیه‎امکانات،خوش‎نقشه , زیرقیمت،وموارددیگر(فریان) 09128351083و22784830"},{"contact":"09104499918ـ44000670","ad_text":"57متر یکخوابه طبقه اول , 8واحدی پذیرایی پرده خور , 3متر پاسیو تراس , بازسازی کامل (داخلی918) , شاهین شمالی 09104499918ـ44000670"},{"contact":"09126160020 ربيعي 44404230","ad_text":"اشرفی اصفهانی -تیراژه , 58متر 2خوابه سوپرلوکس , نقشه فوق العاده دسترسی عالی , طراحی داخلی فول امکانات 09126160020 ربيعي 44404230"},{"contact":"09196537030 (سعيد) 44090404","ad_text":"املاک 133 , کاشانی بهنام , 56متر یکخوابه فول , خوش نقشه آفتابگیر , اکازیون فقط 290میلیون 09196537030 (سعيد) 44090404"},{"contact":"09123173186 و 88684855","ad_text":"آذربایجان - پور مرادیان , 60متر 1خوابه نوساز , 4طبقه تکواحدی - تکی یا یکجا 09123173186 و 88684855"},{"contact":"44277266 مرصاد 09361206463","ad_text":"جیحون امام خمینی , 60 متر 2 خواب تکواحدی , پارکینگ و انباری حیاط , فوری 44277266 مرصاد 09361206463"},{"contact":"55725217","ad_text":"نواب، بریانک، حسام الدین , 57 متر 2 خواب فول امکانات , فروشنده واقعی 55725217"},{"contact":"09138064060 (کامران) 44235071","ad_text":"ستارخان فرعی دنج , 60متر 2خوابه طبقه 5 , آسانسور و انباری , بسیار خوش نقشه فقط 235م 09138064060 (کامران) 44235071"},{"contact":"09381099205 - 88605808","ad_text":"یوسف آباد - مسکن نوین , 60 متر 1 خ , فروشنده واقعی (فربد) 09381099205 - 88605808"},{"contact":"با اسپيلت 09195068353","ad_text":"محدوده میدان شکوفه , 56مترط3 تکواحدی یکخوابه , MDF پارکینگ وانباری کاغذدیواری با اسپيلت 09195068353"},{"contact":"09104499916ـ44000670","ad_text":"سردار جنگل , 57متر یکخوابه باآسانسور , نقشه بی نظیر207م (داخلی916) 09104499916ـ44000670"},{"contact":"09338199766و22790524","ad_text":"اختیاریه , 60متر 1خوابه بدون پارکینگ , وآسانسور 220میلیون (حسینی) 09338199766و22790524"},{"contact":"09356107760ـ44246031","ad_text":"فقط به قیمت توجه کنید!!! , 59 متر سوپرلوکس , پارکینگ و انباری و تراس , فقط و فقط 218م (نوبهار) , ستارخان دریان نو 09356107760ـ44246031"},{"contact":"معيري 09331369470","ad_text":"بهترین موقعیت فردوس غرب , فروش بیواسطه 57 متر , با پارکینگ و انباری معيري 09331369470"},{"contact":"","ad_text":"پونک - عدل , 58متر 1خواب فول 4ساله , خوش نقشه ، پول لازم (خلیلی) , 09125153678و44441486"},{"contact":"09359648784 - 88455545","ad_text":"عباس آباد اندیشه , 60متر1خواب فول امکانات , بینهایت خوش نقشه لوکس(ملکی) 09359648784 - 88455545"},{"contact":"09124772161","ad_text":"کهریزک , 60متر 1خوابه طبقه 2 , فول امکانات نوساز کلیدنخورده 09124772161"},{"contact":"09121121351 - 26203320","ad_text":"سعادت آباد - بلوار فرهنگ , 56 متر یکخواب 10 ساله , پارکینگ انباری متری 7200 (جلیلی 09121121351 - 26203320"},{"contact":"09192592362و22257999","ad_text":"تهرانپارس - پارک پلیس , آپارتمان نقلی لوکس (56متر) , طبقه دوم آسانسور 09192592362و22257999"},{"contact":"09195059054و44170140","ad_text":"پول لازم پول لازم , 58متر / 4ساله / فول امکانات , کم واحد / سالن پرده خور , زیرقیمت فقط259م «علیزاده» , فردوس غرب 09195059054و44170140"},{"contact":"09121099480","ad_text":"خیابان کمالی - خ مخصوص , 60 و90متری نوساز , فول امکانات 09121099480"},{"contact":"09388994676ـ44014952","ad_text":"شهران طوقانی , 58متر یکخوابه فول , بسیار لوکس (نصیری) 09388994676ـ44014952"},{"contact":"09194073693ـ44275100","ad_text":"یک خرید رویایی , 58 متر 2خ فول امکانات , دیزاین شده , فوری 236 م (کیانفر) , جنت آباد (بهترین فرعی) 09194073693ـ44275100"},{"contact":"09120986670 ـ 09338822528","ad_text":"خیابان اجاره دار , 56متر 1خوابه همکف 10ساله , باپارکینگ وانباری اپن کف سرامیک 09120986670 ـ 09338822528"},{"contact":"09198880381 و 22570838","ad_text":"هفده شهریور - گوته , 57متر 1خوابه طبقه2 , 12ساله ، پارکینگ ، انباری 09198880381 و 22570838"},{"contact":"09191388610 - 44800027","ad_text":"پونک , 56متر 1خوابه فول , روبه آفتاب ( شکیبا) 09191388610 - 44800027"},{"contact":"09197737020 - 44622008","ad_text":"فردوس غرب،سازمان برنامه , 57متر 1خواب 4ساله درحدنو , فول امکانات فقط270م (پارسا) 09197737020 - 44622008"},{"contact":"09123031532و44454171","ad_text":"بلوار فردوس - بهار جنوبی , 56متر 1خوابه فول 1ساله , نور مستقیم فقط 290م ( بهزاد) 09123031532و44454171"},{"contact":"09121181715 و 88838583","ad_text":"تهران نو کهن سابق , 2 واحد 60 متری نوساز , فروش یا معاوضه 09121181715 و 88838583"},{"contact":"09124085807و44809533","ad_text":"54و58متر نوساز , سوپر لوکس , مناسب سکونت وسرمایه گذاری , روبه آفتاب - سند آماده(ارشیا) , اشرفی اصفهانی 09124085807و44809533"},{"contact":"09121149518و22226160","ad_text":"میرداماد , 56 متر بی نقص بانورونقشه , عالی + پارکینگ‎وانباری (ساعدی) 09121149518و22226160"},{"contact":"09902039833 و 44268090","ad_text":"مرزداران - لاله , 60 و 70 متر ، 250 م , 55 متر نوساز 310 م (کیانی) 09902039833 و 44268090"},{"contact":"09129351307ـ44246031","ad_text":"این آگهی باورکردنی نیست , 57 متر 2خوابه فول , نورونقشه فراتر از حد تصور , قیمت باورنکردنی252-ابراهیمی , کاشانی اباذر 09129351307ـ44246031"},{"contact":"09337095589","ad_text":"ستاری شمال خیابان مهستان , 60متر یکخواب دیدپارک , تراس،پارکینگ،بیواسطه(250م) 09337095589"},{"contact":"09121900021","ad_text":"پیروزی - بلوار نیکنام , 57متر آسانسور انباری , پارکینگ 4طبقه تکواحدی 151م 09121900021"},{"contact":"09306696854 و 23547","ad_text":"هروی 58متر تک خواب , یکی ازبهترین فرعی های بالای میدان , با امکانات کامل ( مدرس ) 09306696854 و 23547"},{"contact":"09211835202 و 44080430 فروشند واقعي ( آرمان )","ad_text":"آیت ال... کاشانی , 57 متر فول امکانات , 7 سال ساخت , زیرقیمت منطقه 09211835202 و 44080430 فروشند واقعي ( آرمان )"},{"contact":"09359430494 - 44494130","ad_text":"پونک - عدل , 57متر 1خواب کم واحد طبقه 2 , دیزاین شده فقط 280م (احسان) 09359430494 - 44494130"},{"contact":"09350810582ـ44018068","ad_text":"پونک نفت , 60متر یکخوابه طبقه پنجم , فول امکانات (غیاثوند) 09350810582ـ44018068"},{"contact":"09121097893","ad_text":"تهرانپارس - غربیها , 60متر یکخواب کلیدنخورده , کلیه طبقات فوری 09121097893"},{"contact":"09338219310 (رحيمي) 44266080","ad_text":"طرشت بایندریها , 60متر نوساز فول , خوش نقشه سالن پرده خور , فقط وفقط 000 / 000 / 246 09338219310 (رحيمي) 44266080"},{"contact":"88467790","ad_text":"سید خندان - دبستان , 58متر - 1خوابه - انباری , نورگیر عالی -خوش نقشه 88467790"},{"contact":"09390283687ـ44018068","ad_text":"بلوارفردوس شرق ابراهیمی , 59متر2ساله فول نورنقشه استثنایی , 12مترپاسیواختصاصی(داوری) 09390283687ـ44018068"},{"contact":"09126076778","ad_text":"تهرانپارس - خیابان استخر , 57متر دارای آسانسور و پارکینگ , وانباری10سال ساخت بازسازی کامل 09126076778"},{"contact":"09382340824و44404230","ad_text":"جنت آباد مرکزی , 58 و 60 متر 2خوابه نوساز , فول شیک وخوش نقشه (پرهام) 09382340824و44404230"},{"contact":"09124974930ـ44275100","ad_text":"فقط امروز , 57 متر طبقه 3 , نور و نقشه بی نظیر , فوری 188م فوری (سخایی) , جنت آباد 09124974930ـ44275100"},{"contact":"09369194037ـ44266080","ad_text":"فقط با 125م نقد , 60متر طبقه2 رویتی آفتابگیر , نقشه بی نظیر-پارکینگ-انباری , 70وام + 60رهن (مهیار) , فردوس غرب(سازمان برنامه) 09369194037ـ44266080"},{"contact":"شهروز 09121185782","ad_text":"تهرانپارس - غربیها , 60متر یکخواب کلیدنخورده کلیه , طبقات متری 5م پول لازم شهروز 09121185782"}],"آپارتمان-مسکونی-61-تا-65-متر":[{"contact":"09101787789","ad_text":"شریعتی - کشواد , 64 متر 2 خوابه 10 ساله , سند آزاد ، بدون واسطه 09101787789"},{"contact":"رهامي 09125092469","ad_text":"فرشته - کرمعلی , 65 متر 1 خواب , با قدرالسهم 710م با تخفیف رهامي 09125092469"},{"contact":"09192960280","ad_text":"ملک - بهارشیراز 65متر , 2خ کف سرامیک،نوروآفتاب عالی , انباری 43مترحیاط فروش یارهن اجاره 09192960280"},{"contact":"09333959802و44449977","ad_text":"58 و 62 و 69متر نوساز , شخصی ساز سند آماده , لابی شوتینگ ، بالکن و ... , چشم انداز ابدی ( جباری ) , فردوس غرب 09333959802و44449977"},{"contact":"09126194042","ad_text":"بالاتر از میدان ولیعصر , 61 متر موقعیت اداری , 4 طبقه تک واحدی طبقه 4 09126194042"},{"contact":"خانه کوچک 09398177979","ad_text":"قصرالدشت - اکازیون , 65متر2خواب تکواحدباپارکینگ ط4و , انباری ، پکیج ، آشپزخانه فرنیش خانه کوچک 09398177979"},{"contact":"املاک آرتين 09125491600","ad_text":"اشرفی اصفهانی باهنر هجرت , واحدهای 62 - 65 - 67 و 70 , 2 خ فول امکانات زیرقیمت املاک آرتين 09125491600"},{"contact":"09125494278","ad_text":"* پیروزی شکوفه * , 61متر 1خوابه طبقه4 , کف پارکت کاغذدیواری 150م 09125494278"},{"contact":"09125685124 علي 44809533","ad_text":"پیامبر مرکزی - ستاری , 58و65متر1و2خواب نوساز , سند آماده - سالن پرده خور , Best plan 09125685124 علي 44809533"},{"contact":"09907403410ـ44014952","ad_text":"فردوس غرب شقایق , 64متر 2خوابه = 245م , تماس بگیرید (شاهین) 09907403410ـ44014952"},{"contact":"09101364105ـ44090404","ad_text":"املاک 133 , فردوس شرق رامین , 65متر LUX , خوش نقشه پارکینگ , روبه آفتاب انباری , قیمت260میلیون (حکیمی) 09101364105ـ44090404"},{"contact":"09125067662","ad_text":"تهرانپارس 186شرقی , بین133 و 135 دوخواب 64متر , ط4 بدون آسانسور و پارکینگ 09125067662"},{"contact":"23547 و 09211662176","ad_text":"ظفر , بازدید = خرید فقط 550میلیون , 65متر 2خواب نوساز (همرنگ) 23547 و 09211662176"},{"contact":"09121097174","ad_text":"انتهای مطهری - اجاره دار , 64متر 2خوابه , فوری - زیرقیمت 09121097174"},{"contact":"(محمدي) 09129355526","ad_text":"ده ونک , 64متر،تک خواب،3 ساله،فول , LUXE ، محله دنج (محمدي) 09129355526"},{"contact":"09123113125و44809533","ad_text":"62و64و66و68متر2خواب , نوساز + دید شمال و جنوب , آفتابگیر،سالن اجتماعات،لابی , سند آماده (پور جمشید) , فردوس غرب 09123113125و44809533"},{"contact":"09194886684ـ44266080","ad_text":"فقط با75م نقد صاحب خانه شوید , 65متر 2خوابه , پارکینگ انباری تکواحدی , 45دررهن+50 وام ما (مدبر) , کمیل کارون 09194886684ـ44266080"},{"contact":"09123763665","ad_text":"تهرانپارس - بربلوارپروین , 65متر 2خوابه فول امکانات , فول بازسازی شده 09123763665"},{"contact":"09121966269","ad_text":"میدان شهدا ، زرین نعل , 62متری ، خوش نقشه ، انباری , آسانسور ، بالکن ، نماسنگ ، 245م 09121966269"},{"contact":"09106256040 - 77329419","ad_text":"* تهرانپارس مسکن موج آبی * , 65متر2خ فول 3 ساله دارای 50م , وام 70 م رهن « رنجبر» 09106256040 - 77329419"},{"contact":"09195408873 و 88880101","ad_text":"دولت دیباجی , 65متر 1خوابه سوپرلوکس , نوساز نورگیرعالی (نجفی) 09195408873 و 88880101"},{"contact":"09388965325 - 77081190","ad_text":"*تهرانپارس مسکن بزرگ210* , 61متر2خواب 2ساله فول امکانات , بسیارخوش نقشه « صابر» 09388965325 - 77081190"},{"contact":"09376032420 و 23547","ad_text":"میرداماد , 65متر نوساز نورگیر , # زیرقیمت # ستاری 09376032420 و 23547"},{"contact":"09212158523 سليمي 44977226","ad_text":"جنت آباد مرکزی , 65متر 1خواب نوساز , * فوق لاکچری * , بازدید = خرید 09212158523 سليمي 44977226"},{"contact":"09122657912 - 44441671","ad_text":"به قیمت توجه کنید !! , 62متر 2خ کاملاًروبه آفتاب , دسترسی عالی پارکینگ وانباری , فقط وفقط 205م « امیدوار » , شمال فردوس غرب 09122657912 - 44441671"}],"آپارتمان-مسکونی-66-تا-70-متر":[{"contact":"09198701371 متوسل 23547","ad_text":"جلفا (اکازیون ) فوری فوری , 70متر 2خواب بدون پرتی , طبقه سوم متریال عالی , نور بی نهایت 09198701371 متوسل 23547"},{"contact":"09121130316 09101130316","ad_text":"فردوس شرق , 67 متر طبقه سوم , بدون آسانسور , 55 متر قدرالسهم , قیمت مقطوع 950 / 3 09121130316 09101130316"},{"contact":"09375002018 ناجي 88772211","ad_text":"ظفر , 70 متر - دو خواب - 7 ساله , تکواحدی - پارکینگ + ...؟ , فقط 415 میلیون 09375002018 ناجي 88772211"},{"contact":"09196833616","ad_text":"شریعتی - پایین ترازپل صدر , خیابان خاقانی70متر1خواب , 3ساله پارکینگ انباری آسانسور 09196833616"},{"contact":"09192486297 - 88316065","ad_text":"طالقانی - ایرانشهر جنوبی , 70متر 1خوابه 4 ساله فول , قیمت متری 600 / 4 (امیری) 09192486297 - 88316065"},{"contact":"09121125970","ad_text":"بومهن - شهرک طلاییه , 70 متر 3 سال ساخت , با 20 میلیون وام 4 % 09121125970"},{"contact":"09125140414","ad_text":"X ستارخان X , 67متر 2خوابه نوساز تکواحدی , خوش نقشه ازتمام جهات نورگیر 09125140414"},{"contact":"09104977731ـ44969400","ad_text":"فردوس غرب , 70متر2خوابه فول امکانات , کم واحد حتما می پسندید(مسعودی) 09104977731ـ44969400"},{"contact":"09380040219","ad_text":"انتهای خیابان جیحون , 70متر، تکواحدی، 12ساله , ط2،فوری زیرقیمت،بی واسطه 09380040219"},{"contact":"09124212980 و 88880101","ad_text":"ظفر , 70متر خوش نقشه نورگیرعالی , به قیمت رسیده (جهان) 09124212980 و 88880101"},{"contact":"09309581880 - 44741988","ad_text":"شهرزیبا(مسکن آسا) , 70متر1خ برج نوساز،شیک , کلیدنخورده قیمت مناسب(میری 09309581880 - 44741988"},{"contact":"09124403227و44960818","ad_text":"تهرانسر - 17 اصلی , 67متر2خ ط3‎باپارکینگ‎ وانباری , بزرگ،بدون آسانسور(قیمت‎مناسب) 09124403227و44960818"},{"contact":"09373609491ـ44235071","ad_text":"فرعی دنج , 68متر 2خوابه , خوش نقشه غرق در آفتاب , فقط 250 م (نجاریان) , اشرفی اصفهانی 22بهمن 09373609491ـ44235071"},{"contact":"44405805 - 44405802","ad_text":"مسکن هفت پونک , 66 و 68متر 2خ شیک , خوش نقشه بهترین فرعی»شیرازی 44405805 - 44405802"},{"contact":"09367253554و44234422","ad_text":"مرزداران , 68 متر 1خوابه نوساز , توضیحات بیشتر درتماس (رافت) 09367253554و44234422"},{"contact":"33786310","ad_text":"پیروزی نبرد فرزانه , 66متر طبقه دوم فول امکانات , پارکینگ و انباری (املاک قصرنور) 33786310"},{"contact":"44977246 - 09387840228","ad_text":"70میلیون وام آماده !! , ویژه سرمایه گذاری و سکونت , 70وام+ 90رهن+الباقی نقد؟ , 68متر/ 2خ/ نوساز (سهیل) , ( بلوار فردوس غرب ) 44977246 - 09387840228"},{"contact":"09397688898ـ44266080","ad_text":"70متر 2خوابه طبقه 4 , فوق العاده لوکس , بدون هیچ گونه هزینه , فقط و فقط 234 م (شکیبا) , فردوس سازمان جنوبی 09397688898ـ44266080"},{"contact":"09191762476 عباسي 44977137","ad_text":"* بلوار فردوس غرب * , , 67متر / فول / 4ساله , سالن پرده خور 09191762476 عباسي 44977137"},{"contact":"09123103247","ad_text":"آزادی , آپارتمان 70متری سوپرلوکس , فول امکانات فروشی 09123103247"},{"contact":"امير 09126987609","ad_text":"پونک فکوری , 69متر، 2خواب، طبقه1، 3ساله , شیک واستثنایی امير 09126987609"},{"contact":"26153014 - 09125342264","ad_text":"دیباجی - منظریه - لوکس , 70متر 2خوابه 2جهت نور , نوساز فقط630میلیون (سمیر) 26153014 - 09125342264"},{"contact":"09359992858 - 44894485","ad_text":"پایان جستجو !!؟ , 68متر فول کاملاً روبه آفتاب , فرعی کاملا سرسبز / زیرقیمت , منطقه / مقطوع298م «فروغی» , کاشانی - برنامه شمالی 09359992858 - 44894485"},{"contact":"09123485364 ـ 44438484","ad_text":"اشرفی حیدری , 67متر 2خوابه پارکینگ وانباری , 12ساله بازسازی شده (خسروشاهی) 09123485364 ـ 44438484"},{"contact":"09337458022","ad_text":"اشرفی اصفهانی - باهنر , 67متر 2خوابه طبقه3 , فاقد پارکینگ و انباری 09337458022"},{"contact":"09301569738","ad_text":"مشیریه , 70 متر خوش نقشه تکواحدی , باانباری ( فوری فروشی ) 09301569738"},{"contact":"09367194349 - 44441671","ad_text":"به قیمت توجه کنید ! , 70متر 2خ فول امکانات , زیرقیمت منطقه , فقط 350 م « میلاد » , « مرزداران » 09367194349 - 44441671"},{"contact":"09194487408 - 44042912","ad_text":"شهران - کوهسار , 67 متر 2 خوابه فول , 8 ساله فقط 265 م (دادفر) 09194487408 - 44042912"},{"contact":"جلالي 8903 - 09128172594","ad_text":"جردن ( آفریقا ) , 70متربازسازی شده کم واحد , فقط متری 6300 جلالي 8903 - 09128172594"},{"contact":"09363134503 و 23547","ad_text":"جردن - ولیعصر , 68مترفول بهترین طبقه نورعالی , 65مترطبقه سوم فقط550م(جعفری) 09363134503 و 23547"}],"آپارتمان-مسکونی-71-تا-75-متر":[{"contact":"09123196047 - 88282774","ad_text":"گیشا - املاک آشیان , 75متر2خ خوش نقشه , فول امکانات،فرعی زوج وفرد(فیض) 09123196047 - 88282774"},{"contact":"09308502218","ad_text":"نارمک - بر 46متری غربی , 72متر 2خواب 4طبقه تکواحدی , همکف با 12مترحیاط اختصاصی 09308502218"},{"contact":"09126996659","ad_text":"رسالت - کرمان جنوبی , خیابان عقیقی , 75 متری ، طبقه دوم , 84 متری ، طبقه چهارم , 6 ساله ، فول امکانات , متری 500 / 4 09126996659"},{"contact":"09300839008 آراد 44066938","ad_text":"* بلوار فردوس غرب * , (متری فقط 100 / 4 = 300م) , 73متر / فول امکانات , کاملا ، روبه آفتاب ، با بالکن 09300839008 آراد 44066938"},{"contact":"(املاک) 09126000750","ad_text":"رودکی سپه , 72 و 85 متر نوساز , زیرقیمت منطقه (املاک) 09126000750"},{"contact":"09011414842","ad_text":"پونک - شهرک نفت , 72متر 2خ310م پارکینگ , انباری طبقه3 بدون آسانسور 09011414842"},{"contact":"املاک 09124874550","ad_text":"شهرزیبا - تعاون , 71 متر نوساز مناسب برج نشینان , فقط متری 200 / 4 م املاک 09124874550"},{"contact":"اميد 09123447763","ad_text":"پونک - سردار شمال , 75متر 2خ کم واحد طبقه1 , بی‎پارکینگ (فقط268م) اميد 09123447763"},{"contact":"09192665023 هانا 44224422","ad_text":"مرزداران , از 70 الی 115متر , آپارتمانهای بقیمت و زیرقیمت , 09192665023 هانا 44224422"},{"contact":"09125802397 و 23547","ad_text":"شهرک غرب - سپهر , 75متر 2خواب طبقه 2 , پارکینگ وانباری 465م (سلیمی) 09125802397 و 23547"},{"contact":"09355870705","ad_text":"منطقه 22 - شهرک نمونه , 73 متر - نور و نقشه عالی , 265 میلیون 09355870705"},{"contact":"جعفري 09359372221","ad_text":"اختیاریه شمالی , 2واحد 73متری , کلیه امکانات جعفري 09359372221"},{"contact":"09192250799 - 09104760666","ad_text":"میدان 72 نارمک , 73متر طبقه3 بازسازی شده , با پارکینگ و انباری-فروشنده واقعی 09192250799 - 09104760666"},{"contact":"09196514796 - 44800027","ad_text":"جنت آباد مرکزی , 74متر 14سال ساخت , فول امکانات متری 3850 ( هاشمی) 09196514796 - 44800027"},{"contact":"09127172070 ـ 22222111","ad_text":"جنوب میرداماد , 75متر 2خ چندساله , فروشنده واقعی (رضوی) 09127172070 ـ 22222111"},{"contact":"جلالي 09124260093","ad_text":"شهرک غرب - بهاران , 75متر فول امکانات , ( 560میلیون ) جلالي 09124260093"},{"contact":"09904031052 ـ 44208070","ad_text":"73متر 2خواب روبه آفتاب , فول بازسازی ، ط3 + پارکینگ , 43متر قدرالسهم , فقط 230م (ملکی) , فردوس غرب (شقایق) 09904031052 ـ 44208070"},{"contact":"رضايي 09125696724","ad_text":"شهرک جهان نما - 73 متر , 2خ پارکینگ انباری ط1 خوش نقشه , آشپزخانه MDFم ، وام مسکن25م رضايي 09125696724"},{"contact":"09101732464و88370909","ad_text":"شهرک غرب فخار مقدم , 75متر طبقه سوم باآسانسور , فوری فروشی (مرادی) 09101732464و88370909"},{"contact":"09125858746 - 26231650","ad_text":"جردن ولیعصر , 73 متر یکساله فول , 630 میلیون فوری ( امینی ) 09125858746 - 26231650"},{"contact":"09191399228 و 23547","ad_text":"# جردن # , 75متر نوساز , نقشه عالی ( خلعتبری ) 09191399228 و 23547"},{"contact":"09125491429 و 23547","ad_text":"دولت - بلوار کاوه , 73متر ( فوری فروشی ) , 500میلیون ( پاشا ) 09125491429 و 23547"},{"contact":"محبي 09191162925","ad_text":"جردن - ولیعصر (پارک ملت) , 75 متر 1 خواب 11 ساله , پارکینگ و انباری به قیمت مناسب محبي 09191162925"},{"contact":"09192466899 - 88747474","ad_text":"شریعتی روبروی ملک , 75 متر 2 خوابه بازسازی شده , نور نقشه عالی فقط 285 م (طاها) 09192466899 - 88747474"},{"contact":"09124049417 و 66554267","ad_text":"ستارخان - 71متر , طبقه 3 ،پارکینگ وانباری , با کلیه امکانات 09124049417 و 66554267"},{"contact":"پيام 09123148120","ad_text":"چیذر , 75 متر 2 خوابه - فول نوسازی , پارکینگ و انباری ( 430 م ) پيام 09123148120"},{"contact":"09104977712ـ44969400","ad_text":"فردوس غرب پروانه , 74متر 2خوابه , فوری فوری؟؟ (خلج) 09104977712ـ44969400"},{"contact":"09128982326 ونيز 44977246","ad_text":"کاشانی (بهنام) , زیرقیمت تا مدت محدود ! , دیزاین به سلیقه خریدار , 75متر/ 2خ / نوساز/ 10واحدی 09128982326 ونيز 44977246"},{"contact":"09122468186","ad_text":"17شهریور پایین پل محلاتی , 72متر2خواب همکف , خوش نقشه وتمیز 170میلیون 09122468186"},{"contact":"09128912207 ـ 44208070","ad_text":"این آگهی تکرار نشدنی است , 75متر بازسازی شخصی , 2خواب ، طبقه3سندی ، پارکینگ , فقط 360م (فرشاد) , شهرک غرب دادمان 09128912207 ـ 44208070"},{"contact":"09201552017","ad_text":"خیابان اول نیروی هوایی , خیابان حاجیوند 74متر , تکواحدی باانباری طبقه2 تخلیه 09201552017"},{"contact":"09125802397 و 23547","ad_text":"سعادت آباد , 73متر طبقه سیزدهم برج , فقط 470 میلیون ( سلیمی ) 09125802397 و 23547"},{"contact":"09123019467و88713715","ad_text":"جمالزاده شمالی , 75متر2خواب نوساز , نورو نقشه عالی با امکانات(ملایری) 09123019467و88713715"},{"contact":"09375002018 - 88772211","ad_text":"75 متر - دو خوابه , بسیارخوش نقشه بانورگیرعالی , خرید آسان , 230نقد + 85 رهن (ناجی) , ظفر 09375002018 - 88772211"},{"contact":"44977167 - 09129231664","ad_text":"75متر 2خواب فول , لوکس 335میلیون , 65متر 2خواب فول , 285میلیون (بردیا) , کاشانی - آلاله شرقی 44977167 - 09129231664"},{"contact":"23547 و 09354757630","ad_text":"فوری ( قیطریه ) فوری , 75متر ویوی بی نظیر , لابی لوکس.سالن اجتماعات(شهروز) 23547 و 09354757630"},{"contact":"09330415740ـ44275100","ad_text":"عجیب ولی واقعی , 75متر 2خوابه , پارکینگ + انباری , فوری فقط!! 198م (موحد) , اشرفی اصفهانی (باهنر) 09330415740ـ44275100"},{"contact":"09362647233 - 09122014036","ad_text":"نظام آباد , 74متر نوساز فول امکانات , شخصی ساز متری400 / 3 میلیون 09362647233 - 09122014036"},{"contact":"امير 09196461449","ad_text":"اشرفی - 75مترسوپرلوکس , به قیمت رسیده-بهترین دسترسی , متری 500 / 5م امير 09196461449"},{"contact":"کمالي 09121865696","ad_text":"نارمک - گلبرگ شرقی , 75 و 73متر نوساز تمام امکانات , زیرقیمت فوری- فروشنده واقعی کمالي 09121865696"},{"contact":"88702266 - 09125915968","ad_text":"(املاک اهورا) , گیشا 75متر 2خواب , با امکانات زیرقیمت منطقه (وطن) 88702266 - 09125915968"},{"contact":"09128081187و 88658182","ad_text":"جردن - بینظیر.... , 75 متر-کم واحدقدرالسهم دار , قیمت باور نکردنی ! ( لایق ) 09128081187و 88658182"}],"آپارتمان-مسکونی-76-تا-80-متر":[{"contact":"09308279620 - 22382551","ad_text":"سعادت آباد-میدان فرهنگ , 80 متر 2 خ شیک , خوش نقشه و لوکس (فرهاد) 09308279620 - 22382551"},{"contact":"09125503971 ـ 88962496","ad_text":"فاطمی , 80 متر 2 خوابه , با نقشه ایده آل و عالی (شکیبا) 09125503971 ـ 88962496"},{"contact":"09368841595 (تيگران) 22733848","ad_text":"نیاوران (خاص) , 78متر 1خوابه، لاکچری 09368841595 (تيگران) 22733848"},{"contact":"09372119830ـ44275100","ad_text":"مناسب سکونت وسرمایه گذاری , 77متر فول امکانات نوساز , تکواحدی فوری فروشی!!! , 205 م (سعدی) , نواب (ایروانی) 09372119830ـ44275100"},{"contact":"09123456253 ـ 44094912","ad_text":"کاشانی ابتدای شاهین جنوبی , 78متر2خ روبه آفتاب سالن پرده خور , فول امکانات340م (ایمانی) 09123456253 ـ 44094912"},{"contact":"09193144428و44136010","ad_text":"نور ، نقشه و موقعیت استثنایی , 76متر / 2خوابه / فول , 2ساله واقعی - روبه آفتاب , زیرقیمت منطقه...؟!؟«حامد» , فردوس - سازمان برنامه 09193144428و44136010"},{"contact":"09904747414 آريا 23547","ad_text":"( جردن - پیشنهاد ویژه ) , 80متر دو خواب مستر , > 150میلیون زیرقیمت < , 09904747414 آريا 23547"},{"contact":"09350551090و88280505","ad_text":"شهرآرا فوری 80متر 2خ , کم واحد باپارکینگ قدرالسهم عالی , فقط و فقط 330م (مهاجر) 09350551090و88280505"},{"contact":"09120287199و44170140","ad_text":"77متر/2خ/4ساله/روبه آفتاب , فول/کم واحد/بالکن بزرگ , کلا 15واحد،سالن مربع بدون , ضعف ، فقط 350م «احسان» , فردوس‎غرب-بهترین‎دسترسی 09120287199و44170140"},{"contact":"33000815و09197292628","ad_text":"اتوبان محلاتی-عارف شمالی , 77مترطبقه3بدون آسانسور , پارکینگ انباری تکواحدی 33000815و09197292628"},{"contact":"09124407513ـ44266080","ad_text":"76متر Full نوساز , کم واحد آفتابگیر اکازیون , ارسال عکس در صورت تمایل , زیرقیمت منطقه (متین) , شهران طوقانی 09124407513ـ44266080"},{"contact":"09109109099و44416929","ad_text":"شهران - مرادی , 80متر2خ ط5خوش نقشه2ساله , زیر قیمت 335م « یزدان » 09109109099و44416929"},{"contact":"09128107590","ad_text":"(گلبرگ غربی) 78متر2خ , بالکن+انباری فروش فوری , زیرقیمت200م ویارهن کامل60م 09128107590"},{"contact":"09124908100","ad_text":"جردن - پارک ملت , 80 متر 4 ساله , سالن بزرگ روبه آفتاب -ارشیا 09124908100"},{"contact":"09363970846ـ44154740","ad_text":"سازمان برنامه مرکزی , 78متر سوپرلوکس فول , 335 میلیون (محسن) 09363970846ـ44154740"},{"contact":"09124273734","ad_text":"نارمک , 76متر 2 خواب باانباری , طبقه 3 تکواحدی 230م 09124273734"},{"contact":"09123388106 و 22222492","ad_text":"« ظفر - نونهالان » , ( فقط 595م مقطوع) , 80متر 2خواب روبه آفتاب(شیرازی) 09123388106 و 22222492"},{"contact":"09352274433 - 22095599","ad_text":"پونک - همیلا , 80متر 2خوابه , متری 500 / 5 م (ازادی) 09352274433 - 22095599"},{"contact":"09199242544_66121836","ad_text":"ستارخان شادمان , « اکازیون » , 80متر فقط 200م «قهرمانی» 09199242544_66121836"},{"contact":"09125701281 ـ 44208070","ad_text":"78متر روبه آفتاب بسیارتمیز , پارکینگ و انباری ، طبقه4 , خوش نقشه و دلپسند , مقطوع متری 5 / 4م (مجتبی) , شمال مرزداران (اکازیون) 09125701281 ـ 44208070"},{"contact":"09121305780","ad_text":"پنجم نیروهوایی , 80متر 1واحداز3واحدطبقه2 , بی پارکینگ،مناسب سرمایه گذاری 09121305780"},{"contact":"09124216881و44299500","ad_text":"ستارخان -براصلی , فقط متری 800 / 5 , 80 مترطبقه اول فول(یزدانی) 09124216881و44299500"},{"contact":"09125466167 و 23547","ad_text":"# جردن # , 80متر 2خواب نوساز , فقط 800میلیون (موحد) 09125466167 و 23547"},{"contact":"09353242936ـ44275100","ad_text":"خانه رویایی شما , 80 متر پارکینگ و انباری , نور و نقشه بی نظیر , قیمت باورنکردنی226م (میلاد) , طرشت 09353242936ـ44275100"},{"contact":"09122714358 - 44221755","ad_text":"مرزداران , 80متر 5 ساله بدون پرتی , سالن پرده خور (خانم رحیم دوست) 09122714358 - 44221755"},{"contact":"09362125497","ad_text":"اشرفی اصفهانی - 22بهمن , 80متر باتمام امکانات , طبقه 5 متری 200 / 4 فوری 09362125497"},{"contact":"22364335 ـ 09192061371","ad_text":"اشرفی، مرزداران، تعاونی , با160میلیون صاحب آپارتمان , 80و 100متری شوید باسند 22364335 ـ 09192061371"},{"contact":"09376032420 و 23547","ad_text":"میرداماد , 80متر تکواحدی دیدنی , \" زیرقیمت \" ستاری 09376032420 و 23547"},{"contact":"09121391810 - 44412492","ad_text":"(بازدیدفقط با دسته چک)78متر , فول پلان بی نقص/ فرعی دنج , سازه ای بی نظیرازآرشیتکت بنام , فقط متری 700 / 4 « چاوشی » , کاشانی - برنامه شمالی 09121391810 - 44412492"},{"contact":"09192062434 ـ 88962496","ad_text":"فاطمی - زرتشت , 78 متر 2خوابه با انباری , تکواحدی طبقه سوم 340 م (نعمتی) 09192062434 ـ 88962496"},{"contact":"09122499055","ad_text":"نارمک - میدان امامت , 77متر 2خوابه فول امکانات , 13 ساله فروشی 09122499055"},{"contact":"09128438920 و 22563933","ad_text":"دولت , 80متر 2خواب خوش نقشه , دسترسی عالی (دانش) 09128438920 و 22563933"},{"contact":"09190443320","ad_text":"مرزداران املاک شهر , 80متر 2خواب روبه آفتاب , فول امکانات 460م (کاملی) 09190443320"},{"contact":"09197733928 - 44442772","ad_text":"اشرفی - فکوری , 80متر 2خواب کم واحد نورعالی , (فقط و فقط 265م) املاک 09197733928 - 44442772"},{"contact":"09125204313و22761940","ad_text":"هروی - مکران‎ , 1واحد80متری5ساله , باامکانات،فوری،زیرقیمت(بهروزی) 09125204313و22761940"},{"contact":"09126839704","ad_text":"اقدسیه - بلوار اوشان , 68و80متر2خوابه یکساله , باکلیه امکانات - فروشی 09126839704"},{"contact":"09121072756 - 44812561","ad_text":"جنت آباد شمالی(مسکن مرادی) , 78متر 2خواب باپارکینگ و , انباری 10ساله فوری فروشی 09121072756 - 44812561"},{"contact":"09125208396 و 44458211","ad_text":"بلوار مرزداران , 77متر فول 485میلیون , 82متر فول 520میلیون (عسکری) 09125208396 و 44458211"},{"contact":"نوري 09121403350","ad_text":"پونک، همیلا، صفاریان طوسی , 77متر 2خواب طبقه همکف , با مستاجر در رهن + 102 متر , زیر همکف (200 م وام ) , فوری فروشی ، لطفا سایت , و املاک تماس نگیرند نوري 09121403350"},{"contact":"09120378057ـ44892973","ad_text":"جنت آباد بهترین فرعی , 76متر2خوابه روبه آفتاب , فول امکانات 300م (مصدق) 09120378057ـ44892973"},{"contact":"09370330826و44136010","ad_text":"« مالک به شدت پول لازم » , نوسازسندآماده متری580 / 4م , 78مترنقشه درحد100متری , پارکینگ جای 3ماشین«عزیزی» , جنت آباد 09370330826و44136010"},{"contact":"09128331521 و 88779496","ad_text":"ونک - توانیر شمالی , 80متر 2خوابه 3ساله , امکانات کامل زیرقیمت560م(چگینی) 09128331521 و 88779496"},{"contact":"09104977721ـ44969400","ad_text":"کاشانی شاهین , 80متربهترین ودنج ترین فرعی , کم واحد طبقه دوم...؟؟؟ (بداقی) 09104977721ـ44969400"},{"contact":"09351385107 و 23547","ad_text":"80متر پلان استثنائی , فول فرنیش - متریال برند , برج باغ - سازه بی همتا , \" از دست ندهید \" ( خانی ) , ظفر ( خاص و بی نظیر ) 09351385107 و 23547"},{"contact":"09123130278","ad_text":"تهرانپارس - بلوارشاهد , خ شیرود 77متر2خوابه , فول امکانات 09123130278"},{"contact":"09124311972 - 44468345","ad_text":"80متر لوکس , 2ساله بهترین طبقه , غرق در نور و آفتاب , فقط متری 200 / 5 م «حیدری» , پونک - ایران زمین شمالی 09124311972 - 44468345"},{"contact":"09120294086 و 22558770","ad_text":"X پاسداران-اختیاریه شمالی X , 80متر 2خوابه سوپرلوکس , نقشه بسیارعالی فقط570م (کامیار) 09120294086 و 22558770"},{"contact":"09397197042 تبريزي 22209988","ad_text":"قیطریه - حکمت , 80متر 2خواب 1خواب مستر , طبقه3 پارکینگ وانباری15ساله , بازسازی شده (500میلیون) 09397197042 تبريزي 22209988"},{"contact":"09128927848 - 44297006","ad_text":"شمال مرزداران , 78متر کم واحد روبه آفتاب فول , 3ساله،ویو - 450 م (باقری) 09128927848 - 44297006"}],"آپارتمان-مسکونی-81تا-85متر":[{"contact":"09198888005,09198888005","ad_text":"فاطمی نرسیده به میدان سلماس خیابان پیروزه. طبقه سوم. ۸واحد. بازسازی کامل. مساحت زمین ۲۴۵متر. ساختمان شرقی و غربی. فاقد آسانسور.لوکس ومدرن ونورگیری بالا.۵دقیقه تا مترو میدان جهاد. 09198888005,09198888005"},{"contact":"23547 و 09195718757","ad_text":"میرداماد ( فروش زیرقیمت ) , از متراژهای 75 تا 84متر , ازقیمت635تا750میلیون(رحمانی) 23547 و 09195718757"},{"contact":"44977207 - 09128725700","ad_text":"فوری ، نوساز ، فوری !! , 85متر ، فوق لاکچری , شدیدا پول لازم , فقط متری 5میلیون (اقبالی) , جنت آباد (بعثت) 44977207 - 09128725700"},{"contact":"09120890552 طاها 22666126","ad_text":"ولنجک - اکازیون , 85متر 2خواب طراحی شیک 09120890552 طاها 22666126"},{"contact":"جعفري 23547 و 09363134503","ad_text":"جردن , 82متر طبقه5 نور ونقشه عالی , 84مترطبقه4و2 نورونقشه عالی جعفري 23547 و 09363134503"},{"contact":"09121459261 - 22461797","ad_text":"ارتش - لاله , 81مترنوسازمتریال وموقعیت , عالی،بسیارخوش نقشه (محمدی) 09121459261 - 22461797"},{"contact":"09195887969 - 22891000","ad_text":"پشت پارک شریعتی , 83متر نوسازباامکانات کم واحد , خوش نقشه متری 300 / 7م (آقایی 09195887969 - 22891000"},{"contact":"09309762792و44136010","ad_text":"83متر2خ فول،بسیارخوش‎نقشه , دیزاین‎شده واحدی‎متمایزدر , منطقه ،نقشه درحد100متری , قیمت‎فقط متری...؟!؟«ادیب» , کاشانی-سازمان‎برنامه شمالی 09309762792و44136010"},{"contact":"09100069606ـ44266080","ad_text":"این آگهی تکرارنشدنی است , 82متر خوش نقشه طبقه2 , نورونقشه رویایی پول لازم , فقط ‎وفقط متری300 / 3م(امجدی) , فردوس غرب (پروانه) 09100069606ـ44266080"},{"contact":"09013667436 و 23547","ad_text":"جردن - ولیعصر , 85متر نوساز آفتاب گیر , فقط متری10میلیون(آرین نیکو) 09013667436 و 23547"},{"contact":"09123768921 و 22207071","ad_text":"# کامرانیه # , 85متر2خ‎نوسازنقشه90متری،نور , جنوب،بالکن،زیرقیمت،فقط؟؟(موقر) 09123768921 و 22207071"},{"contact":"09128506480ـ44818182","ad_text":"بهترین نقشه سالن پرده خور , 85متر 2خوابه طبقه2 سندی , پارکینگ انباری-دسترسی عالی , قیمت فقط 330 م (هامون) , پونک و شهران 09128506480ـ44818182"},{"contact":"09122346229ـ22222602","ad_text":"ظفر - فرعی عالی , فقط 465 م , 85متر2خ باامکانات (رادمنش) 09122346229ـ22222602"},{"contact":"کيواني 09125353845","ad_text":"بزرگراه رسالت - مجیدیه , 85 و 120متر2خواب نوساز , با امکانات کامل ، زیر قیمت کيواني 09125353845"},{"contact":"09368290550 (صابري) 44034401","ad_text":"مهران فهیمی , به قیمت توجه کنید , 85متر FULL , فقط متری 500 / 5 09368290550 (صابري) 44034401"},{"contact":"09386072677","ad_text":"علی آبادجنوبی-5 / 83متر2خ , ط6باآسانسوروپارکینگ،باسند , تعاونی مسکن،متری500 / 1 م فوری 09386072677"},{"contact":"09127997643 - 77081190","ad_text":"*تهرانپارس مسکن بزرگ210* , 84متر2خ باپارکینگ و انباری , غرب بلواربه قیمت رسیده (پیمان) 09127997643 - 77081190"},{"contact":"09032973367","ad_text":"ایوانکی , یکواحد 85متری طبقه سوم , فروش به صورت نقد و اقساط 09032973367"},{"contact":"09124900939","ad_text":"پیروزی - پرستار , 85متر شخصی ساز , طبقه 4 جنوبی باآسانسور , و انباری - بازسازی کامل , 12سال ساخت , 09124900939"},{"contact":"09125990056 و 22147975","ad_text":"سعادت آباد-بهترین فرعی , 82متر2خوابه خوش نقشه , باامکانات نورگیر (عاشوری) 09125990056 و 22147975"},{"contact":"09121795786 22606361","ad_text":"نازی آباد , 83 متر آپارتمان 2 خوابه 09121795786 22606361"},{"contact":"23547 و 09389291303","ad_text":"دولت - اختیاریه , 85متر 2خواب 2ساله واقعی , دارای امکانات کامل ( باقری ) 23547 و 09389291303"},{"contact":"09125257083","ad_text":"شهرک غرب - دادمان , 84متر2خ پارکینگ‎وانباری 2نبش , کم واحد 540م (امیر علی) 09125257083"},{"contact":"09122186850 - 8903","ad_text":"قیطریه - قلندری , 85 متر - 2 خوابه -نوساز , خوش ساخت - بابایی 09122186850 - 8903"},{"contact":"09331000202 شايان 26202020","ad_text":"سعادت آباد , 85 متر فول , منطقه آرام , مقطوع 550 میلیون تومان 09331000202 شايان 26202020"},{"contact":"09126465007 و 77373718","ad_text":"تهرانپارس214شرقی - کادوس , 83متر 2خوابه طبقه اول نوساز , فول روبه آفتاب 440م (بهنام) 09126465007 و 77373718"},{"contact":"09104499929 (داخلي929) 44000670","ad_text":"فردوس غرب , 84متر2خوابه طبقه ششم , نوساز زیرقیمت منطقه , قیمت 455 میلیون 09104499929 (داخلي929) 44000670"},{"contact":"09121193058و88280606","ad_text":"(مرزداران اکازیون) 85متر , 6ساله 2پارکینگ و 2 انباری , سندی ، فقط متری 700 / 5 (آریا) 09121193058و88280606"},{"contact":"09122006377 - 44403838","ad_text":"اشرفی - منطقه 2 , 85متر 2خ فول نوساز کم واحد , نور ونقشه عالی دنج (فتحعلی) 09122006377 - 44403838"},{"contact":"09124112641","ad_text":"پیروزی - پرستار شمالی , 83متر2خ طبقه3 خوش نقشه , 3ساله باهمه امکانات،فقط مصرف کننده 09124112641"},{"contact":"اديب 09126789260","ad_text":"فرمانیه غربی , 83متر2خ نقشه عالی دیدبینظیر , 500مترمشاعات - فروشنده اديب 09126789260"},{"contact":"09037241467 و 22222492","ad_text":"شریعتی، پشت پارک کوروش , 85متر 4ساله لوکس 530م , 95متر2خ آفتابگیر535م(رضایی) 09037241467 و 22222492"},{"contact":"09398898913 - 44474989","ad_text":"پونک - ایران زمین شمالی , 80 و 85 متر 2 خوابه , فول آخرین بازدید (انصاری) 09398898913 - 44474989"},{"contact":"09127242964و44170140","ad_text":"82متر/2خ/نوسازی شده/لوکس , سالن پرده خور/کم‎واحد/فول , کابینت ‏ممبران / خوش ‎نقشه , فقط348م100رهن«کاکایی» , آیت اله کاشانی - آلاله شرقی 09127242964و44170140"},{"contact":"09124190602","ad_text":"شهرک ولیعصر , 85متر فول امکانات نوساز , 220 میلیون 09124190602"},{"contact":"09125162190","ad_text":"پیروزی،م بروجردی، خ پورعبدی , 82متر،تکواحدی،ط4 با آسانسور , و انباری، 205م با پارکینگ 09125162190"},{"contact":"09120405645 وارسته 23547","ad_text":"دولت - کیکاووس , 85متر خوش نقشه نور عالی 09120405645 وارسته 23547"},{"contact":"ربيعي 09355031723 46093586","ad_text":"بلوار تعاون , * فروش فوق العاده * , 4 واحد از پروژه حکیم , 85 الی 95 متری , با شرایط استثنایی , 120م نقد الباقی اقساط , بدون پرداخت کمیسیون ربيعي 09355031723 46093586"}],"آپارتمان-مسکونی-86تا-90متر":[{"contact":"09013036739 يونسي 44610163","ad_text":"بلوار فردوس , 86متر 2خ کلیدنخورده , فول امکانات , بهترین فرعی-به قیمت رسیده 09013036739 يونسي 44610163"},{"contact":"معيني 09120374300","ad_text":"خ امیر کبیر-نزدیک دریاچه , 88متر،2خواب،خوش نقشه , ویو عالی به دریاچه و پارک چیتگر معيني 09120374300"},{"contact":"09192974765 - 26231650","ad_text":"فوری ( جردن ) فوری , 90 متر 2 خواب سوپرلوکس , با ویو عالی ( بابایی ) 09192974765 - 26231650"},{"contact":"09123370430 - 44891226","ad_text":"پونک - عدل , 88متر فول روبه آفتاب , نقشه بی نظیر - بالکن دار (رامین) 09123370430 - 44891226"},{"contact":"23547 و 09123339818","ad_text":">< دولت - کیکاووس >< , 90متر 2پارکینگ , فقط 777 میلیون ( آرشام ) 23547 و 09123339818"},{"contact":"09121889161و22742449","ad_text":"دزاشیب (متروتجریش) , از تولید به مصرف (نوساز) , 87متر2خواب(سالن اجتماعات و ...) 09121889161و22742449"},{"contact":"محبوب 09128387412","ad_text":"گیشا - املاک 2000 , 90متر 2خ نوساز , شیک،خوش نقشه،فروشنده واقعی محبوب 09128387412"},{"contact":"09121790599","ad_text":"رسالت-خیابان نیرو دریایی , اکازیون , 90متر نوساز بی واسطه 09121790599"},{"contact":"09127220233 خادميان 22410971","ad_text":"زعفرانیه , 90 متر 2 خواب نوساز , 20 متر حیاط خلوت , فول امکانات - به قیمت 09127220233 خادميان 22410971"},{"contact":"09392433172ـ44034401","ad_text":"جنت آباد چهارباغ شرقی , 86متر / 2خوابه / نوساز , فول امکانات / دیدنی (منوچهری) 09392433172ـ44034401"},{"contact":"طبي 09361660908","ad_text":"سعادت آباد - ایثار شمالی , 90 و 80 متری برج باغ , ویو عالی ، بهترین متریال طبي 09361660908"},{"contact":"09308813397 سعيدي 23547","ad_text":"شمال جردن - بهترین فرعی , نوساز بسیار شیک , 86متر 2خواب فول , بهترین طبقه - کم واحد 09308813397 سعيدي 23547"},{"contact":"09128301332و66556208","ad_text":"ستارخان 88متر فول امکانات , نوساز قیمت باورنکردنی , فقط متری 500 / 3 (مسکن) 09128301332و66556208"},{"contact":"09123046715 ـ 44257838","ad_text":"لوکس ترین واحد منطقه , 90متر نوساز طبقه سوم , روبه آفتاب ، سالن پرده خور , فقط متری 7م (کاووسی) , مرزداران (فرعی دنج) 09123046715 ـ 44257838"},{"contact":"09120473440ـ44034401","ad_text":"90متر نوساز دوطرف نور , دسترسی استثنایی , 200نقد + 110 رهن , + الباقی توافقی (مهرنیا) , پونک جنت آباد 09120473440ـ44034401"},{"contact":"09357713138و44234422","ad_text":"شهرک ژاندارمری , 90متر2خ نقشه بی نظیرفروشنده , واقعی ومواردمشابه(داریوش) 09357713138و44234422"},{"contact":"09123783502 - 88455545","ad_text":"سهروردی ملک , 90متر2خوابه فول امکانات خوش , نقشه نورگیرعالی اکازیون(پارسا) 09123783502 - 88455545"},{"contact":"09212264147 (شکوهي) 44034401","ad_text":"جنت آباد جنوبی , به قیمت ترین واحد منطقه , 90متر نوساز , مقطوع «435م» مقطوع 09212264147 (شکوهي) 44034401"},{"contact":"09122400906 و 22222492","ad_text":"« میرداماد - جنوب » , 90متر2پارکینگ لوکس730م , 85متر2ساله لوکس680م(کیان) 09122400906 و 22222492"},{"contact":"املاک 09126341153","ad_text":"شهرزیبا - تعاون , 87 متر نوسازمناسب برج نشینان , فقط متری 200 / 4 املاک 09126341153"},{"contact":"09305065006و44454171","ad_text":"پونک - همیلا , 88متر 2خوابه 12ساله , فول بازسازی ( میثم ) 09305065006و44454171"},{"contact":"09126976990 - 22898665","ad_text":"آزادی , 90 متر 2 خواب , با امکانات (نعمتی) 09126976990 - 22898665"},{"contact":"09193783478 منور 23547","ad_text":"ظفر , 88متر 2خواب فول امکانات , نوساز , فقط 620میلیون 09193783478 منور 23547"},{"contact":"09102220415 قدس 88582131","ad_text":"گروه نور , شهرک غرب - فلامک شمالی , 90متر2خواب،زیرهمکف , بانورخوب،زیرقیمت , تکواحدی ، موقعیت عالی 09102220415 قدس 88582131"},{"contact":"09381270267","ad_text":"بلوار فردوس - رامین جنوبی , 5 / 85 متر 2 خ فوق العاده لوکس , فول چندساله کم واحد ( 395 م ) 09381270267"},{"contact":"09306348393 و 22604707","ad_text":"کیکاووس , 90متر2خواب طبقه دوم , پارکینگ،انباری، بازسازی شده (رها) 09306348393 و 22604707"},{"contact":"09383432665 و 26154212","ad_text":"نیاوران - جمشیدیه , 90متر 2خوابه تکواحدی , فول امکانات ( نجفی ) 09383432665 و 26154212"},{"contact":"09352076700 و 23547","ad_text":"شمال هروی - وفامنش , 90مترلوکس آفتابگیرنقشه عالی , بازسازی کامل فقط 540م(ساعی) 09352076700 و 23547"},{"contact":"09017015859 - 88030033","ad_text":"شیخ بهایی و زعفرانیه , 90 تا 200 متر ، نوساز ، لوکس , بهترین متریال،قیمت ؟ (دوستی) 09017015859 - 88030033"},{"contact":"09338104734 - 44441671","ad_text":"# قیمت ها شکسته شد # , 90متر / 5ساله / فول , زیرقیمت منطقه , فقط * 300 / 4 م * «شکیبا» , فردوس غرب 09338104734 - 44441671"},{"contact":"09125391156ـ44818182","ad_text":"88 متر نوساز , دنج به معنای واقعی , نورونقشه عالی 470 م , 200نقد الباقی توافقی (رستمی) , پونک شاهین 09125391156ـ44818182"},{"contact":"09126840846ـ44330104","ad_text":"شهران (مسکن پارسه) , 88متر 2خوابه فول , 90رهن+ 80وام +220نقد(عبدی) 09126840846ـ44330104"},{"contact":"09195018040 و 22605152","ad_text":"« دولت - کیکاووس » , 90متر 2خواب نوساز فول , کم واحد - موارد مشابه (کریمی) 09195018040 و 22605152"},{"contact":"09128448623ـ22222602","ad_text":"شمال میرداماد , 90متر نورشمال و جنوب ط 1 , باقدرالسهم 620م (پویان) 09128448623ـ22222602"},{"contact":"09355728618 سليمي 26209597","ad_text":"قیطریه * سهیل * , 90متر نوساز , بهترین فرعی نورعالی , فروشنده واقعی واقعی 09355728618 سليمي 26209597"},{"contact":"هاشمي 44977296 09902795339","ad_text":"* بلوار فردوس غرب * , روبه آفتاب / لاکچری , 86متر / نوساز / ویو ابدی , فقط 430میلیون هاشمي 44977296 09902795339"},{"contact":"صدرا 09332200232و8903","ad_text":"90 متر دو خواب , 2 پارکینگ - سراسر نور , فول مشاعات - دیدنی , فقط 770 میلیون , قیطریه - روشنایی صدرا 09332200232و8903"},{"contact":"09195590160و22736505","ad_text":"تجریش دربند , 90متر 2خواب تکواحدی , نوساز شیک (غفاری) 09195590160و22736505"},{"contact":"09123976905 22560193","ad_text":"پشت پارک قیطریه , خیابان صفا , 4دستگاه 90 و 130متری , 10ساله , 09123976905 22560193"},{"contact":"09101572164","ad_text":"گیشا , 90 متری 2 خوابه نوساز , بسیار خوش نقشه ، فول امکانات 09101572164"},{"contact":"09351668374 (مختاري) 44034401","ad_text":"جنت آباد , 86متر نوساز , یک سوپر ملک واقعی , با قیمت عالی !!! 09351668374 (مختاري) 44034401"},{"contact":"09385014244 و 23547","ad_text":"ظفر.فریدافشار.بهترین فرعی , 86متر 2خ نور و نقشه عالی , به قیمت رسیده (حاجی زاده) 09385014244 و 23547"},{"contact":"09121873363","ad_text":"* جنت آباد شمالی * , 90متر , نقد و اقساط با چک 09121873363"},{"contact":"09365226543 عادل 23547","ad_text":"ظفر , \"\" اکازیون قیمت \"\" , 90متر , > 150میلیون زیرقیمت < 09365226543 عادل 23547"}],"آپارتمان-مسکونی-91تا-95متر":[{"contact":"09356467636و22925969","ad_text":"پاسداران بلوار شهرزاد , 95متر2خ2ساله،فرعی دنج و , خوش نقشه،متری600 / 8م(فتحی) 09356467636و22925969"},{"contact":"09125115345 - 66595598","ad_text":"جمالزاده شمالی - خیابان زند , 5 / 92متر دوخوابه تکواحدی , طبقه3 بالکن انباری پارکینگ 09125115345 - 66595598"},{"contact":"09122262017 - 88741215","ad_text":"سهروردی جنوبی - ملک , 94متر 8 ساله Full , تخلیه « 520 میلیون » (کوشا) 09122262017 - 88741215"},{"contact":"09123905639","ad_text":"سرسبز مینو نبش 49 , 93متر 2خوابه با انباری و , 2پارکینگ (متری 400 / 5م) 09123905639"},{"contact":"09122479617 - 09126202069","ad_text":"طرشت - سماء , 93متر2خواب طبقه2 فول امکانات , 50رهن مالک + 270نقد 09122479617 - 09126202069"},{"contact":"09123062876","ad_text":"اقدسیه - کوی لاله , 95متر 2خوابه نورونقشه عالی , بیواسطه فوری فروشی 550 م 09123062876"},{"contact":"09128037674 ـ 26753185","ad_text":"ازگل - بهترین کوچه باغ , 94 متر 2 خ خوش نقشه , نورعالی-ویو بی نظیر-محمودی 09128037674 ـ 26753185"},{"contact":"09126868610","ad_text":"تهرانپارس 196غربی , 94متر3سال ساخت فول امکانات , 100م وام + 100 رهن 09126868610"},{"contact":"پيام 09353354900","ad_text":"× دریان نو همایونشهرجنوبی × , 93متر یکساله , 2 پارکینگ بادیزاین پيام 09353354900"},{"contact":"09122049905و44136010","ad_text":"« پول لازم » , 94متر/ 2خواب/فول امکانات , فوق العاده شیک , فقط متری900 / 3م «بیک» , کاشانی - آلاله شرقی 09122049905و44136010"},{"contact":"چگيني 09388475758","ad_text":"خواجه عبدا... و جلفا , 80 تا 130 متری باامکانات , نوساز و چندساله چگيني 09388475758"},{"contact":"املاک 09101435343","ad_text":"شهرزیبا - تعاون , 91 متر نوساز مناسب برج نشینان , فقط متری 200 / 4 املاک 09101435343"},{"contact":"09372006343 - 09122024395","ad_text":"توحید , 91متر زیرهمکف 2خوابه مسکونی , موقعیت اداری باتمام امکانات 09372006343 - 09122024395"},{"contact":"09021464978","ad_text":"آیت اله کاشانی بهنام 12 , مجموعه آبشار آپارتمان 94متر , نوساز پارکینگ و انباری فروشی 09021464978"},{"contact":"ساعي09352076700و23547","ad_text":"هروی - مکران ( فوری ) , 95متر تکواحدی لوکس 1ساله , روبه آفتاب امکانات فول فقط550م ساعي09352076700و23547"},{"contact":"09199086143 و 26209597","ad_text":"جردن , 92متر - 2خ - چندساله , باامکانات-متری 800 / 6 قاسمی 09199086143 و 26209597"},{"contact":"09120294086 و 22558770","ad_text":"دروس - لوکس , 95متر 2خوابه بازسازی شده , فقط 680میلیون (کامیار) 09120294086 و 22558770"},{"contact":"09351196580 رسولي 8903","ad_text":"دولت - فرعی دنج , 93متر2خواب نورعالی , نقشه فوق العاده , قیمت باورنکردنی 09351196580 رسولي 8903"},{"contact":"09191485562","ad_text":"پونک فروش قطعی , 95متری سازه فوق العاده , فول امکانات، مرحله نما 09191485562"},{"contact":"88914253","ad_text":"میدان ولیعصر - کوچه روشن , 95متر2خواب کف ونماسنگ , طبقه3آسانسورانباری 460م 88914253"},{"contact":"09194625850و44136010","ad_text":"اکازیون - زیر قیمت , 94متر / فول امکانات /3ساله , فوق العاده شیک / کم واحد , فقط متری200 / 5م «کیانی» , کاشانی-سازمان برنامه شمالی 09194625850و44136010"},{"contact":"09127659134 و 26209597","ad_text":"# فرشته # , 95متر - ویوابدی-نورگیر , متری 800 / 10 (همتی) 09127659134 و 26209597"},{"contact":"09197653193 ـ 44208070","ad_text":"95متر 2خواب 3ساله , نقشه عالی ، 2 کله نور , فول امکانات ، زیرقیمت , فقط و فقط 428م (آشوری) , ستارخان (بهترین فرعی) 09197653193 ـ 44208070"},{"contact":"ماني 09126201822","ad_text":"یوسف آباد , 95 متر نور و نقشه عالی , 2 پارکینگ سندی ماني 09126201822"},{"contact":"09121942621 - 09351875126","ad_text":"گیشا - فروشنده واقعی , 94متر کلیدنخورده،فول امکانات , بر خیابان اصلی 09121942621 - 09351875126"},{"contact":"09365336851 - 88747474","ad_text":"سهروردی شمالی ( 7 ساله) , 94 متر 2 خ فول امکانات , باورکنید فقط 470 م (ابتکار) 09365336851 - 88747474"},{"contact":"09121022614 09121240338","ad_text":"مرزداران (نوساز) , سازه ای لوکس - کلید نخورده , پلان تفکیکی، سالن پرده خور , مناسب سکونت با موقعیت اداری , فروش بصورت تک یا یکجا 09121022614 09121240338"},{"contact":"09372153457 روشن 22082082","ad_text":"سعادت آباد.صرافهای شمالی , 92متر2خواب+18مترتراس , از مجموعه ای خاص , بازسازی شده.سونا و جکوزی 09372153457 روشن 22082082"},{"contact":"09011777085 فردمنش 23547","ad_text":"هروی - ساقدوش , 91متر 2خواب طبقه 4 فول , ژنراتور مرکزی , روف گاردن 09011777085 فردمنش 23547"},{"contact":"09194452574و22221719","ad_text":"دولت - جهانتاب , متری 9 م مقطوع , 95متر - ساخت عالی (جاوید) 09194452574و22221719"},{"contact":"09122194152 - 88280660","ad_text":"گیشا - اکازیون , 95متر فول نوساز روبه آفتاب , زیرقیمت؟!!! (علوی) 09122194152 - 88280660"},{"contact":"09354438719 نريمان 88747474","ad_text":"بهارشمالی 91 متر , 4 ساله - سازه فوق العاده , آفتابگیر - انباری + آسانسور , خوش نقشه فقط 430 م 09354438719 نريمان 88747474"},{"contact":"تماس عصر 88083445 صفوي 0019494125973","ad_text":"*میر داماد - اکازیون* , » فروشنده واقعی زیر قیمت « , 91متر2خ نوسازلابی مجلل لوکس , 2 نبش امکانات کامل فقط770م , تماس صبح 8الی12با شماره زیر تماس عصر 88083445 صفوي 0019494125973"},{"contact":"09122982136","ad_text":"تهرانسر , 95 مترنوساز با امکانات , پارکینگ و انباری فوری فروشی 09122982136"},{"contact":"09128706429 و 44298300","ad_text":"مرزداران , 95متر 2خواب آفتابگیر , سالن پرده خور (محمدزاده) 09128706429 و 44298300"},{"contact":"09122710235 و 22000785","ad_text":"کیکاووس - اثنی عشری , 94متر 9ساله بی نظیر , 675 میلیون (پیله وری) 09122710235 و 22000785"},{"contact":"عباس 09125039806","ad_text":"پیامبر غربی - شاهین جنوبی , 100و91مترنوسازباکلیه امکانات , باساخت اکازیون متری 800 / 6 عباس 09125039806"},{"contact":"09123783714","ad_text":"گرمدره - فوری فروشی , 95مترخوش نقشه ،نورگیر،پارکینگ , انباری‎،آسانسورتکمیل‎متری400 / 1 09123783714"},{"contact":"09124242466 - 22395975","ad_text":"دیباجی جنوبی تسلیمی , 92متر 2خ 11ساله , نور و نقشه عالی ( اوسط ) 09124242466 - 22395975"},{"contact":"23547 و 09192703614","ad_text":"جردن 95متر , کلید نخورده فول , فروش فوری زیرقیمت منطقه(دهقان) 23547 و 09192703614"}],"آپارتمان-مسکونی-96تا-100متر":[{"contact":"09203715354","ad_text":"اقدسیه- اوشان- طاق کسرا آپارتمان طبقه ششم، به سمت جنوب دید کل تهران. تمیز خالی و آماده تحویل، ۱۲ متر پارکینگ، ۴ متر انباری. دارای مجتمع ورزشی استخر سونا جکوزی، محوطه مناسب، سند شش دانک ۱۳۷۹. دسترسی به تاکسی، اتوبوس اقدسیه ابتدای بزرک راه ارتش انتهای بلوار اوشان کوی رضوان 09203715354"},{"contact":"09397992693 و 22224800","ad_text":"پاسداران زمرد(اکازیون) , 100متر2خ نوساز،فول،فرعی‎ دنج , ومشجر،فوری زیرقیمت(محرمی) 09397992693 و 22224800"},{"contact":"44979976 09198128195","ad_text":"سازمان برنامه مرکزی , 100متر 1ساله کلیدنخورده , خوش نقشه و نورگیر , قیمت 600میلیون 44979976 09198128195"},{"contact":"09120612996و44136010","ad_text":"« زیر قیمت کارشناسی » , 100متر 8 ساله فول امکانات , روبه آفتاب - شیک و دیدنی , قیمت واقعااستثنایی!؟!«راد» , فردوس غرب - سازمان برنامه 09120612996و44136010"},{"contact":"09124859117 و 22563933","ad_text":"قیطریه - دستور , 100متر 2خواب نورودیدعالی , پلان عالی لابی لوکس«زیرقیمت» جاوید 09124859117 و 22563933"},{"contact":"09361531324 - 44251350","ad_text":"مناسب سرمایه گذاری و سکونت , 100 متر 2 خواب , FULL ، کم واحد , فقط 345 م (فتاحی) , ستارخان 09361531324 - 44251350"},{"contact":"09358401381و88713715","ad_text":"ولنجک , 100متر2 خواب(نوساز) , خوش نقشه فول امکانات(اسماعیلی) 09358401381و88713715"},{"contact":"09391780661 - 22883070","ad_text":"پاسداران - هروی , 95متر، 2خواب، نو و چندساله , نقشه و نورعالی، با امکانات(حیدری) 09391780661 - 22883070"},{"contact":"سروش 09122481059","ad_text":"\" گیشا \" , 100 متر 2ساله روبه آفتاب , در بهترین طبقه فقط 700 م سروش 09122481059"},{"contact":"پايدار 09104542605","ad_text":"دیباجی - منظریه , 95متر 3 ساله - 105متر نوساز , 2 خوابه 100 % فروشنده - املاک پايدار 09104542605"},{"contact":"09125833937 و 22391500","ad_text":"قیطریه ( اکازیون ) , 97متر بهترین فرعی سهیل , خوش نقشه ، آفتابگیر- تهرانی 09125833937 و 22391500"},{"contact":"09123774297 (ابراهيمي) 88741215","ad_text":"سهروردی شمالی - سیبویه , 100متر 2خ طبقه 2 روی‎همکف , تکواحدی-شیک‏وپرنور- 20ساله , پارکینگ - انباری (500م) 09123774297 (ابراهيمي) 88741215"},{"contact":"09122108995 رستگار 23547","ad_text":"قیطریه - پارک , 100متر فقط 700 میلیون 09122108995 رستگار 23547"},{"contact":"املاک 88045230","ad_text":"مرزداران , 100متر، 2خواب , باامکانات کامل، اکازیون املاک 88045230"},{"contact":"09113939787 - 88741215","ad_text":"سهروردی‎شمالی - پالیزی , 100متر با آسانسور و انباری , فول بازسازی شده 610م(شمس) 09113939787 - 88741215"},{"contact":"09123156851 و 22082082","ad_text":"114متر تک واحدی 900م , 98متر چند ساله 500م , 65متر 2خوابه 550م , بهترینها نزد ماست!!! (پیروز) , سعادت آباد - شهرک غرب 09123156851 و 22082082"},{"contact":"09198099180 - 44144878","ad_text":"کاشانی - تعاونی , 96متر2خ2ساله کم واحد،فول , امکانات،فروشنده واقعی (مهران) 09198099180 - 44144878"},{"contact":"09123219858 - 26154212","ad_text":"نیاوران ( تکواحدی ) , ( اکازیون منطقه ) , 100متر 2خ نوساز , طبقه5 سندآماده , نوراز2طرف , سالن اجتماعات ( سیامک ) 09123219858 - 26154212"},{"contact":"احسني 44979984 09120198600","ad_text":"* بلوار فردوس شرق * , استثنایی فوری !! , 97متر / فول / 4ساله/ لوکس , احسني 44979984 09120198600"},{"contact":"09331000269 بي آزار 26202020","ad_text":"دولت , 100 متر فول , نور، پلان و متریال عالی , فقط متری 800 / 6 09331000269 بي آزار 26202020"},{"contact":"09212930252 - 88280660","ad_text":"گیشا - فرعی زوج , 96متر 4ساله خوش نقشه , موقعیت عالی،قیمت مناسب(دریانی) 09212930252 - 88280660"},{"contact":"09127880311 اسلامي 88701690","ad_text":"کردستان-فرعی خوب , 100متر 2خواب نور ونقشه عالی 09127880311 اسلامي 88701690"},{"contact":"09125868901 - 88741215","ad_text":"شریعتی - جلفا , 100متر 2خوابه تکواحد , باپارکینگ‎وانباری500م (مبین) 09125868901 - 88741215"},{"contact":"09123265693 و 23547","ad_text":"هروی ( اکازیون ) , 96متر یک ساله 2پارکینگ , آفتابگیر 740میلیون ( علیپور ) 09123265693 و 23547"},{"contact":"09354829060 - 26315520","ad_text":"شمس آباد - ریحانی , 96متر،2خ،باپارکینگ،انباری , آسانسور،روبه آفتاب(آرمین) 09354829060 - 26315520"},{"contact":"09198292100 - 88060254","ad_text":"یوسف آباد , 100 متر 2خوابه , درحدنو - زیرقیمت(راد) 09198292100 - 88060254"},{"contact":"09192277481 ـ 44208070","ad_text":"100متر 2خواب ، فول , بسیار خوش نقشه , ویو ابدی بینظیر , فقط و فقط 340م (سجاد) , آریاشهر برج لوکس 09192277481 ـ 44208070"},{"contact":"مهران 09123997734","ad_text":"ملاصدرا-شیراز(اکازیون) , 100 متر 2 خوابه بهترین طبقه , کم واحد آفتابگیر فوری فروشی مهران 09123997734"},{"contact":"09391506478و88280505","ad_text":"شهرآرا فوری , 98متر 2خ فول 1ساله , زیرقیمت فقط 550م (سعیدی) 09391506478و88280505"},{"contact":"09123029692 و 88544000","ad_text":"سهروردی شمالی , 100متر2خ بازسازی شده , لوکس،فقط فقط 430م - مقدم 09123029692 و 88544000"},{"contact":"09108690510و44291967","ad_text":"جنت آباد جنوبی , 100متر 2خ نور و نقشه عالی , فرعی دنج و مشجر « شهریار » 09108690510و44291967"},{"contact":"محمدي 09123812049","ad_text":"پونک - همیلا , 96متر فول امکانات , بدون مشرف محمدي 09123812049"},{"contact":"09126863042 تاران 88772211","ad_text":"« ظفر » , 100متری های دو خواب منطقه , چند ساله و نوساز ...؟؟!! , 09126863042 تاران 88772211"},{"contact":"09125371450و22581402","ad_text":"نارمک , 90 الی 100 متر 5 طبقه , 2واحد فول امکانات (اسدی) 09125371450و22581402"},{"contact":"09122560072 و 26763961","ad_text":"( املاک یوسفیان ) , سعادت آباد-علامه شمالی 100متر , 2خ نورگیرعالی بازسازی شده(رئیسی) 09122560072 و 26763961"},{"contact":"09306696854 و 23547","ad_text":"هروی - آزادی , 96متر 2خواب , با امکانات و 2پارکینگ (مدرس) 09306696854 و 23547"},{"contact":"09394623204ـ44266080","ad_text":"تکواحدی بخرید , 99متر لوکس پارکینگ , انباری بالکن روبه آفتاب , بازسازی کامل فقط375م (رامین) , اشرفی باغ فیض 09394623204ـ44266080"},{"contact":"09194931367 - 44977137","ad_text":", 100متر تکواحدی !! , سازنده به نام منطقه , (فقط متری 900 / 3م ! ) آریا , * صادقیه - بلوار فردوس * 09194931367 - 44977137"},{"contact":"09104499946ـ44000670","ad_text":"ستاری پیامبر , 100متر2خوابه نوساز فول , کم واحد سوپرلوکس (داخلی946) 09104499946ـ44000670"},{"contact":"09104537708","ad_text":"جنت آبادمرکزی - بلواربعثت , 96متر2خواب14ساله طبقه4 , بدون آسانسور متری 5 / 3 م 09104537708"},{"contact":"09195826833","ad_text":"اتوبان بابایی - شهرک البرز , 98متر 2خ نوساز استخر وسونا , پارکینگ و انباری متری 4 م 09195826833"},{"contact":"09120188906 ديبا 44610163","ad_text":"شاهین شمالی , 100متر 2خ نوساز , نقشه بینظیر - روبه آفتاب , فرعی دنج بازدید=خرید 09120188906 ديبا 44610163"},{"contact":"09366688108و26700118","ad_text":"دروس - یارمحمدی , فقط 740میلیون , 100متر2خ تکواحدی , دربهترین فرعی یارمحمدی , بسیارشیک وخوش نقشه , فروشنده پول لازم (شاهین) 09366688108و26700118"},{"contact":"9124946619 - 88772211","ad_text":"ونک ( به قیمت رسیده ) , 100متر 2 خواب لوکس , روبه آفتاب فقط 650 م زمانی 9124946619 - 88772211"},{"contact":"09382705608 پارسا 26209597","ad_text":"# قیطریه # , 100متر-2خوابه-نقشه بینظیر , موقعیت استثنایی ، لوکس , تماس = شرح توضیحات 09382705608 پارسا 26209597"},{"contact":"09123080213و44136010","ad_text":"فقط و فقط 400 / 4 فوری , 100متر/2خ/فول / کم واحد , سراسرپرده خور،واقعادیدنی , بازدید = قرارداد «فلاح» , جنت آباد،چهار باغ شرقی 09123080213و44136010"},{"contact":"09191264623 - 88741215","ad_text":"شریعتی - دولت , 100متر2خوابه همکف،تکواحدی , با انباری (گرامی) 09191264623 - 88741215"},{"contact":"09364363036 - 22883070","ad_text":"دروس , 100متر، 2خ، نوساز، رو به آفتاب , فقط متری 500 / 8 (فرزاد) 09364363036 - 22883070"},{"contact":"09199395247","ad_text":"مهرآباد جنوبی ، 100متر , 2 خوابه بسیار شیک تکواحدی , 2ساله فول متری3م 09199395247"},{"contact":"26154070 - 26154060","ad_text":"کاملیا 4 - آجودانیه , برج های مسکونی - تجاری , 99متری - دیدابدی , خوش نقشه ، متریال درجه 1 , فقط متری 500 / 6 , با اقساط 3ساله 26154070 - 26154060"},{"contact":"09195727511 و 23547","ad_text":"میرداماد , 100متر ( فوری ) , 780میلیون ( یاشار ) 09195727511 و 23547"},{"contact":"09368858126 - 44894590","ad_text":"( خرید طلایی امروز ) , 100متر فول - کم واحد , چندساله کاملاً روبه آفتاب , متری 800 / 4 م «رمضانی» , فردوس غرب - برنامه مرکزی 09368858126 - 44894590"},{"contact":"09193608793و44136010","ad_text":"فوری فروشی , 96متر / نوساز / سند آماده , نور و نقشه عالی / طبقه سوم , قیمت مقطوع600 / 4م«سینا» , جنت آباد - شاهین 09193608793و44136010"},{"contact":"09123455284 - 22047383","ad_text":"فرشته - دسترسی عالی , 100مترط بالا نورونقشه بی نظیر , به قیمت رسیده (تهرانی) 09123455284 - 22047383"},{"contact":"09331000214 موسوي 26202020","ad_text":"( شهرک غرب ) , متریال فوق العاده , 100 متری نوساز فول , 1 میلیارد 09331000214 موسوي 26202020"},{"contact":"09122213258و44205323","ad_text":"مرزداران اطاعتی , 100 متر 2خ 9ساله کم واحدنور , و نقشه عالی باکلیه امکانات(صمدی) 09122213258و44205323"},{"contact":"09190396936 - 88741215","ad_text":"سهروردی جنوبی (97متر) , یک‎ساله فول لابی‎مجلل , تماس= 100 %خریدایده‎آل-فرخی 09190396936 - 88741215"},{"contact":"09367961885و 44458211","ad_text":"اشرفی - بالاتر از حکیم , 98متر نوساز کم واحد , سوپرلوکس و عالی ( کیان ) 09367961885و 44458211"},{"contact":"09120143620 و 26209597","ad_text":"ولنجک , 100متر-2خوابه-فول بازسازی , دارای قدرالسهم فقط؟!ونکی 09120143620 و 26209597"},{"contact":"09304079505و44286145","ad_text":"اشرفی - منطقه2 , 97متر لوکس-دسترسی عالی , فروشنده واقعی (محمد) 09304079505و44286145"}]}